MANIFEST.in
README.txt
setup.cfg
setup.py
c2/__init__.py
c2.app.shorturl.egg-info/PKG-INFO
c2.app.shorturl.egg-info/SOURCES.txt
c2.app.shorturl.egg-info/dependency_links.txt
c2.app.shorturl.egg-info/entry_points.txt
c2.app.shorturl.egg-info/namespace_packages.txt
c2.app.shorturl.egg-info/not-zip-safe
c2.app.shorturl.egg-info/requires.txt
c2.app.shorturl.egg-info/top_level.txt
c2/app/__init__.py
c2/app/shorturl/__init__.py
c2/app/shorturl/config.py
c2/app/shorturl/configure.zcml
c2/app/shorturl/interfaces.py
c2/app/shorturl/version.txt
c2/app/shorturl/browser/__init__.py
c2/app/shorturl/browser/configlet.py
c2/app/shorturl/browser/configure.zcml
c2/app/shorturl/browser/createbox.pt
c2/app/shorturl/browser/createbox.py
c2/app/shorturl/browser/shorturl_view.py
c2/app/shorturl/content/__init__.py
c2/app/shorturl/content/configure.zcml
c2/app/shorturl/content/interfaces.py
c2/app/shorturl/content/shorturl.py
c2/app/shorturl/content/shorturlfolder.py
c2/app/shorturl/profiles/default/catalog.xml
c2/app/shorturl/profiles/default/componentregistry.xml
c2/app/shorturl/profiles/default/controlpanel.xml
c2/app/shorturl/profiles/default/factorytool.xml
c2/app/shorturl/profiles/default/metadata.xml
c2/app/shorturl/profiles/default/rolemap.xml
c2/app/shorturl/profiles/default/types.xml
c2/app/shorturl/profiles/default/viewlets.xml
c2/app/shorturl/profiles/default/workflows.xml
c2/app/shorturl/profiles/default/types/ShortUrl.xml
c2/app/shorturl/profiles/default/types/ShortUrlFolder.xml
c2/app/shorturl/tests/__init__.py
c2/app/shorturl/tests/_tests.py
c2/app/shorturl/tests/base.py
c2/app/shorturl/tests/test_add_content_types.py
c2/app/shorturl/tests/test_setup.py
docs/HISTORY.txt
docs/INSTALL.txt
docs/LICENSE.GPL
docs/LICENSE.txt