Metadata-Version: 1.0
Name: c2.app.shorturl
Version: 1.0a3
Summary: Create a Short URL for Plone content
Home-page: http://bitbucket.org/cmscom/c2.app.shorturl
Author: Manabu TERADA
Author-email: terada@cmscom.jp
License: GPL
Keywords: plone zope shorturl
Platform: UNKNOWN
Classifier: Framework :: Plone
Classifier: Programming Language :: Python
